MANIFEST.in
README.md
requirements.txt
setup.py
keras_piecewise/__init__.py
keras_piecewise/backend.py
keras_piecewise/piecewise.py
keras_piecewise.egg-info/PKG-INFO
keras_piecewise.egg-info/SOURCES.txt
keras_piecewise.egg-info/dependency_links.txt
keras_piecewise.egg-info/requires.txt
keras_piecewise.egg-info/top_level.txt
tests/__init__.py
tests/test_pool_1d.py
tests/test_pool_2d.py
tests/test_rnn.py
tests/util.py