Metadata-Version: 2.1
Name: keras-piecewise
Version: 0.14.0
Summary: A wrapper layer for splitting and accumulating sequential data
Home-page: https://github.com/CyberZHG/keras-piecewise
Author: CyberZHG
Author-email: CyberZHG@users.noreply.github.com
License: MIT
Platform: UNKNOWN
Classifier: Programming Language :: Python :: 3
Classifier: License :: OSI Approved :: MIT License
Classifier: Operating System :: OS Independent
